torchbox/version.py
torchbox/__init__.py
torchbox/nn/activations.c
torchbox/nn/activations.cpython-310-x86_64-linux-gnu.so
torchbox/nn/__init__.py
torchbox/nn/activations.pyi
torchbox/spl/voptimizer.c
torchbox/spl/spfunction.cpython-310-x86_64-linux-gnu.so
torchbox/spl/spfunction.pyi
torchbox/spl/spfunction.c
torchbox/spl/__init__.py
torchbox/spl/voptimizer.pyi
torchbox/spl/voptimizer.cpython-310-x86_64-linux-gnu.so
torchbox/dsp/normalsignals.c
torchbox/dsp/ffts.cpython-310-x86_64-linux-gnu.so
torchbox/dsp/kernels.cpython-310-x86_64-linux-gnu.so
torchbox/dsp/correlation.cpython-310-x86_64-linux-gnu.so
torchbox/dsp/convolution.cpython-310-x86_64-linux-gnu.so
torchbox/dsp/convolution.pyi
torchbox/dsp/polynomialfit.pyi
torchbox/dsp/interpolation.c
torchbox/dsp/convolution.c
torchbox/dsp/function_base.c
torchbox/dsp/ffts.pyi
torchbox/dsp/kernels.c
torchbox/dsp/interpolation.cpython-310-x86_64-linux-gnu.so
torchbox/dsp/window_function.c
torchbox/dsp/function_base.pyi
torchbox/dsp/window_function.cpython-310-x86_64-linux-gnu.so
torchbox/dsp/polynomialfit.cpython-310-x86_64-linux-gnu.so
torchbox/dsp/normalsignals.pyi
torchbox/dsp/function_base.cpython-310-x86_64-linux-gnu.so
torchbox/dsp/ffts.c
torchbox/dsp/window_function.pyi
torchbox/dsp/__init__.py
torchbox/dsp/correlation.pyi
torchbox/dsp/polynomialfit.c
torchbox/dsp/kernels.pyi
torchbox/dsp/correlation.c
torchbox/dsp/interpolation.pyi
torchbox/dsp/normalsignals.cpython-310-x86_64-linux-gnu.so
torchbox/base/typevalue.c
torchbox/base/baseops.c
torchbox/base/mathops.c
torchbox/base/baseops.cpython-310-x86_64-linux-gnu.so
torchbox/base/randomfunc.c
torchbox/base/arrayops.pyi
torchbox/base/randomfunc.pyi
torchbox/base/typevalue.pyi
torchbox/base/randomfunc.cpython-310-x86_64-linux-gnu.so
torchbox/base/arrayops.cpython-310-x86_64-linux-gnu.so
torchbox/base/mathops.pyi
torchbox/base/baseops.pyi
torchbox/base/__init__.py
torchbox/base/arrayops.c
torchbox-1.1.27.dist-info/top_level.txt
torchbox-1.1.27.dist-info/METADATA
torchbox-1.1.27.dist-info/RECORD
torchbox-1.1.27.dist-info/WHEEL
torchbox-1.1.27.dist-info/LICENSE
